sopel_modules.lastfm-0.2.0-py3.7-nspkg.pth
sopel_modules/lastfm/__init__.py
sopel_modules/lastfm/lastfm.py
tests/__init__.py
tests/test_lastfm.py
sopel_modules.lastfm-0.2.0.dist-info/COPYING
sopel_modules.lastfm-0.2.0.dist-info/METADATA
sopel_modules.lastfm-0.2.0.dist-info/WHEEL
sopel_modules.lastfm-0.2.0.dist-info/namespace_packages.txt
sopel_modules.lastfm-0.2.0.dist-info/top_level.txt
sopel_modules.lastfm-0.2.0.dist-info/RECORD
