Metadata-Version: 2.1
Name: sopel-modules.lastfm
Version: 0.2.0
Summary: A sopel plugin that returns the user's last listened track
Home-page: https://github.com/shanedabes/sopel-lastfm
Author: Shane Donohoe
Author-email: shane@donohoe.cc
License: Eiffel Forum License, version 2
Platform: UNKNOWN
Requires-Dist: sopel (<7,>=6.0)
